discord_sentry_reporting/__init__.py
discord_sentry_reporting-2.0.4.dist-info/LICENSE
discord_sentry_reporting-2.0.4.dist-info/METADATA
discord_sentry_reporting-2.0.4.dist-info/WHEEL
discord_sentry_reporting-2.0.4.dist-info/top_level.txt
discord_sentry_reporting-2.0.4.dist-info/RECORD
