Metadata-Version: 2.1
Name: discord-sentry-reporting
Version: 2.0.4
Summary: A small compatibility library that provides functionality to report errors from discord.py to Sentry.
Home-page: https://github.com/RDIL/bluejay
Author: Reece Dunham
Author-email: me@rdil.rocks
License: MIT
Keywords: discord,sentry,error,reporting,compat
Platform: UNKNOWN
Requires-Dist: sentry-sdk
